lemur/__about__.py
lemur/__init__.py
lemur/constants.py
lemur/database.py
lemur/default.conf.py
lemur/exceptions.py
lemur/extensions.py
lemur/factory.py
lemur/manage.py
lemur/metrics.py
lemur/models.py
lemur/pytest.py
lemur/schemas.py
lemur/utils.py
lemur/acme_providers/__init__.py
lemur/acme_providers/cli.py
lemur/api_keys/__init__.py
lemur/api_keys/cli.py
lemur/api_keys/models.py
lemur/api_keys/schemas.py
lemur/api_keys/service.py
lemur/api_keys/views.py
lemur/auth/__init__.py
lemur/auth/ldap.py
lemur/auth/permissions.py
lemur/auth/service.py
lemur/auth/views.py
lemur/authorities/__init__.py
lemur/authorities/models.py
lemur/authorities/schemas.py
lemur/authorities/service.py
lemur/authorities/views.py
lemur/authorizations/__init__.py
lemur/authorizations/models.py
lemur/authorizations/service.py
lemur/certificates/__init__.py
lemur/certificates/cli.py
lemur/certificates/hooks.py
lemur/certificates/models.py
lemur/certificates/schemas.py
lemur/certificates/service.py
lemur/certificates/utils.py
lemur/certificates/verify.py
lemur/certificates/views.py
lemur/common/__init__.py
lemur/common/celery.py
lemur/common/defaults.py
lemur/common/fields.py
lemur/common/health.py
lemur/common/managers.py
lemur/common/missing.py
lemur/common/redis.py
lemur/common/schema.py
lemur/common/utils.py
lemur/common/validators.py
lemur/defaults/__init__.py
lemur/defaults/schemas.py
lemur/defaults/views.py
lemur/deployment/__init__.py
lemur/deployment/service.py
lemur/destinations/__init__.py
lemur/destinations/models.py
lemur/destinations/schemas.py
lemur/destinations/service.py
lemur/destinations/views.py
lemur/dns_providers/__init__.py
lemur/dns_providers/cli.py
lemur/dns_providers/models.py
lemur/dns_providers/schemas.py
lemur/dns_providers/service.py
lemur/dns_providers/util.py
lemur/dns_providers/views.py
lemur/domains/__init__.py
lemur/domains/models.py
lemur/domains/schemas.py
lemur/domains/service.py
lemur/domains/views.py
lemur/endpoints/__init__.py
lemur/endpoints/models.py
lemur-1.8.2.dist-info/AUTHORS
lemur-1.8.2.dist-info/LICENSE
lemur-1.8.2.dist-info/METADATA
lemur-1.8.2.dist-info/WHEEL
lemur-1.8.2.dist-info/entry_points.txt
lemur-1.8.2.dist-info/top_level.txt
lemur-1.8.2.dist-info/RECORD
